heroes_profile_replay_uploader/__init__.py
heroes_profile_replay_uploader/py.typed
heroes_profile_replay_uploader/uploader.py
heroes_profile_replay_uploader-0.2.2.dist-info/METADATA
heroes_profile_replay_uploader-0.2.2.dist-info/WHEEL
heroes_profile_replay_uploader-0.2.2.dist-info/entry_points.txt
heroes_profile_replay_uploader-0.2.2.dist-info/licenses/LICENSE
heroes_profile_replay_uploader-0.2.2.dist-info/RECORD
