Metadata-Version: 2.4
Name: heroes-profile-replay-uploader
Version: 0.2.2
Summary: A command line uploader for Heroes of the Storm replays to heroesprofile.com
Project-URL: Repository, https://gitlab.com/dawalters/heroes-profile-replay-uploader
Maintainer: Dom Walters
License-File: LICENSE
Keywords: heroes,heroesprofile,hots,replay,uploader
Classifier: Development Status :: 4 - Beta
Classifier: License :: OSI Approved :: MIT License
Classifier: Programming Language :: Python :: 3
Classifier: Programming Language :: Python :: 3.11
Classifier: Programming Language :: Python :: 3.12
Classifier: Programming Language :: Python :: 3.13
Requires-Python: >=3.11
Requires-Dist: requests==2.32.3
Requires-Dist: xdg-base-dirs==6.0.2
Provides-Extra: dev
Requires-Dist: pre-commit==4.1.0; extra == 'dev'
Provides-Extra: lint-and-format
Requires-Dist: ruff==0.9.9; extra == 'lint-and-format'
Provides-Extra: static-analysis
Requires-Dist: mypy==1.15.0; extra == 'static-analysis'
Requires-Dist: types-requests==2.32.0.20250306; extra == 'static-analysis'
